CHANGELOG.md
LICENSE
README.md
config.yml
eredesscraper/__init__.py
eredesscraper/_version.py
eredesscraper/agent.py
eredesscraper/api.py
eredesscraper/backend.py
eredesscraper/cli.py
eredesscraper/config_schema.yml
eredesscraper/db_clients.py
eredesscraper/ddb_init.sql
eredesscraper/meta.py
eredesscraper/models.py
eredesscraper/openapi.json
eredesscraper/server.py
eredesscraper/utils.py
eredesscraper/workflows.py
pyproject.toml
requirements.txt
eredesscraper-1.0.1.dist-info/LICENSE
eredesscraper-1.0.1.dist-info/METADATA
eredesscraper-1.0.1.dist-info/WHEEL
eredesscraper-1.0.1.dist-info/entry_points.txt
eredesscraper-1.0.1.dist-info/RECORD
