Metadata-Version: 2.1
Name: eredesscraper
Version: 1.0.1
Summary: Web scraper to extract data from E-REDES website and load it into database storage.
Home-page: https://github.com/rf-santos/eredes-scraper
License: MIT
Keywords: web,scraper,influxdb,database,electricity,energy,e-redes
Author: Ricardo Filipe dos Santos
Author-email: ricardofilipecdsantos@gmail.com
Requires-Python: >=3.11,<3.13
Classifier: License :: OSI Approved :: MIT License
Classifier: Programming Language :: Python :: 3
Classifier: Programming Language :: Python :: 3.11
Classifier: Programming Language :: Python :: 3.12
Requires-Dist: duckdb (>=0.10.2,<0.11.0)
Requires-Dist: fastapi (>=0.110.0,<0.111.0)
Requires-Dist: influxdb-client (>=1.38.0,<2.0.0)
Requires-Dist: openpyxl (>=3.1.2,<4.0.0)
Requires-Dist: pandas (>=2.1.1,<3.0.0)
Requires-Dist: playwright (>=1.44.0,<2.0.0)
Requires-Dist: playwright-stealth (>=1.0.6,<2.0.0)
Requires-Dist: pykwalify (>=1.8.0,<2.0.0)
Requires-Dist: python-multipart (>=0.0.9,<0.0.10)
Requires-Dist: pyyaml (>=6.0.1,<7.0.0)
Requires-Dist: screeninfo (>=0.8.1,<0.9.0)
Requires-Dist: typer[all] (>=0.9.0,<0.10.0)
Requires-Dist: uvicorn (>=0.28.0,<0.29.0)
Project-URL: Documentation, https://github.com/rf-santos/eredes-scraper
Project-URL: Repository, https://github.com/rf-santos/eredes-scraper
